CHANGES.txt
DESCRIPTION.rst
LICENSE.txt
MANIFEST.in
README.md
setup.py
foruse/__init__.py
foruse/colors.py
foruse/configparser.py
foruse/datelib.py
foruse/error.py
foruse/lib.py
foruse/log.py
foruse/watch.py
foruse.egg-info/PKG-INFO
foruse.egg-info/SOURCES.txt
foruse.egg-info/dependency_links.txt
foruse.egg-info/requires.txt
foruse.egg-info/top_level.txt